redis_limiter/__init__.py
redis_limiter-0.0.3.dist-info/LICENSE
redis_limiter-0.0.3.dist-info/METADATA
redis_limiter-0.0.3.dist-info/WHEEL
redis_limiter-0.0.3.dist-info/top_level.txt
redis_limiter-0.0.3.dist-info/RECORD
