Metadata-Version: 2.1
Name: redis-limiter
Version: 0.0.3
Summary: A Redis based rate limiter implementation for Python
Home-page: https://github.com/laobaox/redis-limiter
Author: bao xie
Requires-Python: >=2.7.9
License-File: LICENSE
